{
  "obsidian-git:commit": [
    {
      "modifiers": [
        "Mod",
        "Shift"
      ],
      "key": "C"
    }
  ],
  "obsidian-git:push2": [
    {
      "modifiers": [
        "Mod",
        "Shift"
      ],
      "key": "P"
    }
  ],
  "editor:set-heading-2": [
    {
      "modifiers": [
        "Alt"
      ],
      "key": "2"
    }
  ],
  "editor:insert-mathblock": [
    {
      "modifiers": [
        "Alt",
        "Shift"
      ],
      "key": "4"
    }
  ],
  "editor:set-heading-1": [
    {
      "modifiers": [
        "Alt"
      ],
      "key": "1"
    }
  ],
  "editor:set-heading-3": [
    {
      "modifiers": [
        "Alt"
      ],
      "key": "3"
    }
  ],
  "editor:set-heading-4": [
    {
      "modifiers": [
        "Alt"
      ],
      "key": "4"
    }
  ],
  "editor:set-heading-5": [
    {
      "modifiers": [
        "Alt"
      ],
      "key": "5"
    }
  ],
  "editor:set-heading-6": [
    {
      "modifiers": [
        "Alt"
      ],
      "key": "6"
    }
  ],
  "editor:set-heading-0": [
    {
      "modifiers": [
        "Alt"
      ],
      "key": "0"
    }
  ],
  "editor:insert-codeblock": [
    {
      "modifiers": [
        "Alt"
      ],
      "key": "`"
    }
  ],
  "quickadd:choice:00ed47d7-400b-4635-a5fb-e8408c0a6d6a": [
    {
      "modifiers": [
        "Mod"
      ],
      "key": "Y"
    }
  ]
}